gym_trading_env/__init__.py
gym_trading_env/downloader.py
gym_trading_env/environments.py
gym_trading_env/renderer.py
gym_trading_env/templates/index.html
gym_trading_env/utils/__init__.py
gym_trading_env/utils/charts.py
gym_trading_env/utils/history.py
gym_trading_env/utils/portfolio.py
gym_trading_env-0.3.5.dist-info/LICENSE.txt
gym_trading_env-0.3.5.dist-info/METADATA
gym_trading_env-0.3.5.dist-info/WHEEL
gym_trading_env-0.3.5.dist-info/top_level.txt
gym_trading_env-0.3.5.dist-info/RECORD
