Metadata-Version: 2.2
Name: gym-trading-env
Version: 0.3.5
Summary: A simple, easy, customizable Open IA Gym environments for trading.
Author-email: Clement Perroud <clement.perroud.pro@gmail.com>
License: MIT License
Project-URL: Homepage, https://github.com/ClementPerroud/Gym-Trading-Env
Project-URL: Bug Tracker, https://github.com/ClementPerroud/Gym-Trading-Env/issues
Classifier: Programming Language :: Python :: 3
Classifier: License :: OSI Approved :: MIT License
Classifier: Operating System :: OS Independent
Requires-Python: >=3.7
License-File: LICENSE.txt
Requires-Dist: pandas>=1.5.3
Requires-Dist: numpy>=1.21.1
Requires-Dist: gymnasium>=0.28.1
Requires-Dist: flask==2.2.5
Requires-Dist: pyecharts>=2.0.2
Requires-Dist: ccxt==3.0.59
Requires-Dist: nest_asyncio
